aws_redshift_schema_explorer/__init__.py
aws_redshift_schema_explorer/_version.py
aws_redshift_schema_explorer/api.py
aws_redshift_schema_explorer/constants.py
aws_redshift_schema_explorer/explore.py
aws_redshift_schema_explorer/model.py
aws_redshift_schema_explorer/paths.py
aws_redshift_schema_explorer/sql/__init__.py
aws_redshift_schema_explorer/sql/s01_01_list_database.sql
aws_redshift_schema_explorer/sql/s02_01_list_schema.sql
aws_redshift_schema_explorer/sql/s03_01_list_table_on_native_database_from_native_schema.sql
aws_redshift_schema_explorer/sql/s03_02_list_table_or_view_on_native_database_from_shared_schema.sql
aws_redshift_schema_explorer/sql/s04_01_list_columns.sql
aws_redshift_schema_explorer/vendor/__init__.py
aws_redshift_schema_explorer/vendor/pytest_cov_helper.py
aws_redshift_schema_explorer-0.1.1.dist-info/AUTHORS.rst
aws_redshift_schema_explorer-0.1.1.dist-info/LICENSE.txt
aws_redshift_schema_explorer-0.1.1.dist-info/METADATA
aws_redshift_schema_explorer-0.1.1.dist-info/WHEEL
aws_redshift_schema_explorer-0.1.1.dist-info/RECORD
